odoo/addons/agreement_sale/README.rst
odoo/addons/agreement_sale/__init__.py
odoo/addons/agreement_sale/__manifest__.py
odoo/addons/agreement_sale/i18n/agreement_sale.pot
odoo/addons/agreement_sale/i18n/es.po
odoo/addons/agreement_sale/i18n/es_AR.po
odoo/addons/agreement_sale/i18n/it.po
odoo/addons/agreement_sale/i18n/zh_CN.po
odoo/addons/agreement_sale/models/__init__.py
odoo/addons/agreement_sale/models/res_config_settings.py
odoo/addons/agreement_sale/models/sale.py
odoo/addons/agreement_sale/readme/CONTRIBUTORS.rst
odoo/addons/agreement_sale/readme/DESCRIPTION.rst
odoo/addons/agreement_sale/readme/ROADMAP.rst
odoo/addons/agreement_sale/security/ir.model.access.csv
odoo/addons/agreement_sale/static/description/icon.png
odoo/addons/agreement_sale/static/description/index.html
odoo/addons/agreement_sale/views/agreement.xml
odoo/addons/agreement_sale/views/res_config_settings.xml
odoo/addons/agreement_sale/views/sale_order.xml
odoo14_addon_agreement_sale-14.0.1.0.1.dev12.dist-info/METADATA
odoo14_addon_agreement_sale-14.0.1.0.1.dev12.dist-info/WHEEL
odoo14_addon_agreement_sale-14.0.1.0.1.dev12.dist-info/top_level.txt
odoo14_addon_agreement_sale-14.0.1.0.1.dev12.dist-info/RECORD
